{
  "metadata": {
    "levelId": "l-chalki",
    "levelName": "Chalki",
    "generatedAt": "2026-01-01T10:54:05.550Z",
    "expeditionId": "x-old-world",
    "expeditionName": "Old World"
  },
  "outcomes": {
    "lost": 2749,
    "won-hard": 5206,
    "won-normal": 11450
  },
  "players": 19405,
  "feedbacks": {
    "1": 61,
    "2": 25,
    "3": 62,
    "4": 208,
    "5": 740
  },
  "turnsToVictory": {
    "normal": [
      {
        "turns": 1,
        "players": 0
      },
      {
        "turns": 2,
        "players": 0
      },
      {
        "turns": 3,
        "players": 0
      },
      {
        "turns": 4,
        "players": 0
      },
      {
        "turns": 5,
        "players": 0
      },
      {
        "turns": 6,
        "players": 0
      },
      {
        "turns": 7,
        "players": 0
      },
      {
        "turns": 8,
        "players": 3
      },
      {
        "turns": 9,
        "players": 38
      },
      {
        "turns": 10,
        "players": 179
      },
      {
        "turns": 11,
        "players": 529
      },
      {
        "turns": 12,
        "players": 806
      },
      {
        "turns": 13,
        "players": 1015
      },
      {
        "turns": 14,
        "players": 1065
      },
      {
        "turns": 15,
        "players": 1044
      },
      {
        "turns": 16,
        "players": 1064
      },
      {
        "turns": 17,
        "players": 885
      },
      {
        "turns": 18,
        "players": 762
      },
      {
        "turns": 19,
        "players": 658
      },
      {
        "turns": 20,
        "players": 532
      },
      {
        "turns": 21,
        "players": 507
      },
      {
        "turns": 22,
        "players": 388
      },
      {
        "turns": 23,
        "players": 294
      },
      {
        "turns": 24,
        "players": 283
      },
      {
        "turns": 25,
        "players": 234
      },
      {
        "turns": 26,
        "players": 169
      },
      {
        "turns": 27,
        "players": 136
      },
      {
        "turns": 28,
        "players": 129
      },
      {
        "turns": 29,
        "players": 109
      },
      {
        "turns": 30,
        "players": 75
      },
      {
        "turns": 31,
        "players": 63
      },
      {
        "turns": 32,
        "players": 60
      },
      {
        "turns": 33,
        "players": 59
      },
      {
        "turns": 34,
        "players": 44
      },
      {
        "turns": 35,
        "players": 28
      },
      {
        "turns": 36,
        "players": 25
      },
      {
        "turns": 37,
        "players": 28
      },
      {
        "turns": 38,
        "players": 23
      },
      {
        "turns": 39,
        "players": 20
      },
      {
        "turns": 40,
        "players": 20
      },
      {
        "turns": 41,
        "players": 17
      },
      {
        "turns": 42,
        "players": 18
      },
      {
        "turns": 43,
        "players": 13
      },
      {
        "turns": 44,
        "players": 13
      },
      {
        "turns": 45,
        "players": 5
      },
      {
        "turns": 46,
        "players": 9
      },
      {
        "turns": 47,
        "players": 5
      },
      {
        "turns": 48,
        "players": 7
      },
      {
        "turns": 49,
        "players": 8
      },
      {
        "turns": 50,
        "players": 6
      }
    ],
    "hard": [
      {
        "turns": 1,
        "players": 0
      },
      {
        "turns": 2,
        "players": 0
      },
      {
        "turns": 3,
        "players": 0
      },
      {
        "turns": 4,
        "players": 0
      },
      {
        "turns": 5,
        "players": 0
      },
      {
        "turns": 6,
        "players": 0
      },
      {
        "turns": 7,
        "players": 0
      },
      {
        "turns": 8,
        "players": 4
      },
      {
        "turns": 9,
        "players": 20
      },
      {
        "turns": 10,
        "players": 60
      },
      {
        "turns": 11,
        "players": 174
      },
      {
        "turns": 12,
        "players": 340
      },
      {
        "turns": 13,
        "players": 464
      },
      {
        "turns": 14,
        "players": 510
      },
      {
        "turns": 15,
        "players": 496
      },
      {
        "turns": 16,
        "players": 468
      },
      {
        "turns": 17,
        "players": 407
      },
      {
        "turns": 18,
        "players": 338
      },
      {
        "turns": 19,
        "players": 304
      },
      {
        "turns": 20,
        "players": 245
      },
      {
        "turns": 21,
        "players": 212
      },
      {
        "turns": 22,
        "players": 164
      },
      {
        "turns": 23,
        "players": 151
      },
      {
        "turns": 24,
        "players": 125
      },
      {
        "turns": 25,
        "players": 105
      },
      {
        "turns": 26,
        "players": 86
      },
      {
        "turns": 27,
        "players": 63
      },
      {
        "turns": 28,
        "players": 77
      },
      {
        "turns": 29,
        "players": 48
      },
      {
        "turns": 30,
        "players": 43
      },
      {
        "turns": 31,
        "players": 26
      },
      {
        "turns": 32,
        "players": 40
      },
      {
        "turns": 33,
        "players": 26
      },
      {
        "turns": 34,
        "players": 19
      },
      {
        "turns": 35,
        "players": 18
      },
      {
        "turns": 36,
        "players": 21
      },
      {
        "turns": 37,
        "players": 20
      },
      {
        "turns": 38,
        "players": 17
      },
      {
        "turns": 39,
        "players": 14
      },
      {
        "turns": 40,
        "players": 15
      },
      {
        "turns": 41,
        "players": 6
      },
      {
        "turns": 42,
        "players": 7
      },
      {
        "turns": 43,
        "players": 10
      },
      {
        "turns": 44,
        "players": 8
      },
      {
        "turns": 45,
        "players": 4
      },
      {
        "turns": 46,
        "players": 2
      },
      {
        "turns": 47,
        "players": 2
      },
      {
        "turns": 48,
        "players": 2
      },
      {
        "turns": 49,
        "players": 0
      },
      {
        "turns": 50,
        "players": 4
      }
    ]
  }
}