{
  "metadata": {
    "levelId": "l-heritage",
    "levelName": "Heritage",
    "generatedAt": "2025-02-28T17:32:39.514Z",
    "expeditionId": "x-old-world",
    "expeditionName": "Old World"
  },
  "outcomes": {
    "lost": 5286,
    "won-hard": 5009,
    "won-normal": 16636
  },
  "players": 26931,
  "feedbacks": {
    "1": 93,
    "2": 36,
    "3": 94,
    "4": 317,
    "5": 1146
  },
  "turnsToVictory": {
    "normal": [
      {
        "turns": 1,
        "players": 0
      },
      {
        "turns": 2,
        "players": 0
      },
      {
        "turns": 3,
        "players": 0
      },
      {
        "turns": 4,
        "players": 0
      },
      {
        "turns": 5,
        "players": 0
      },
      {
        "turns": 6,
        "players": 0
      },
      {
        "turns": 7,
        "players": 16
      },
      {
        "turns": 8,
        "players": 86
      },
      {
        "turns": 9,
        "players": 349
      },
      {
        "turns": 10,
        "players": 834
      },
      {
        "turns": 11,
        "players": 1401
      },
      {
        "turns": 12,
        "players": 1690
      },
      {
        "turns": 13,
        "players": 1597
      },
      {
        "turns": 14,
        "players": 1395
      },
      {
        "turns": 15,
        "players": 1328
      },
      {
        "turns": 16,
        "players": 1193
      },
      {
        "turns": 17,
        "players": 1060
      },
      {
        "turns": 18,
        "players": 878
      },
      {
        "turns": 19,
        "players": 713
      },
      {
        "turns": 20,
        "players": 635
      },
      {
        "turns": 21,
        "players": 538
      },
      {
        "turns": 22,
        "players": 466
      },
      {
        "turns": 23,
        "players": 393
      },
      {
        "turns": 24,
        "players": 310
      },
      {
        "turns": 25,
        "players": 255
      },
      {
        "turns": 26,
        "players": 239
      },
      {
        "turns": 27,
        "players": 204
      },
      {
        "turns": 28,
        "players": 163
      },
      {
        "turns": 29,
        "players": 123
      },
      {
        "turns": 30,
        "players": 111
      },
      {
        "turns": 31,
        "players": 77
      },
      {
        "turns": 32,
        "players": 73
      },
      {
        "turns": 33,
        "players": 60
      },
      {
        "turns": 34,
        "players": 59
      },
      {
        "turns": 35,
        "players": 40
      },
      {
        "turns": 36,
        "players": 35
      },
      {
        "turns": 37,
        "players": 27
      },
      {
        "turns": 38,
        "players": 36
      },
      {
        "turns": 39,
        "players": 35
      },
      {
        "turns": 40,
        "players": 27
      },
      {
        "turns": 41,
        "players": 17
      },
      {
        "turns": 42,
        "players": 23
      },
      {
        "turns": 43,
        "players": 14
      },
      {
        "turns": 44,
        "players": 18
      },
      {
        "turns": 45,
        "players": 19
      },
      {
        "turns": 46,
        "players": 12
      },
      {
        "turns": 47,
        "players": 10
      },
      {
        "turns": 48,
        "players": 10
      },
      {
        "turns": 49,
        "players": 7
      },
      {
        "turns": 50,
        "players": 6
      }
    ],
    "hard": [
      {
        "turns": 1,
        "players": 0
      },
      {
        "turns": 2,
        "players": 0
      },
      {
        "turns": 3,
        "players": 0
      },
      {
        "turns": 4,
        "players": 0
      },
      {
        "turns": 5,
        "players": 0
      },
      {
        "turns": 6,
        "players": 0
      },
      {
        "turns": 7,
        "players": 54
      },
      {
        "turns": 8,
        "players": 176
      },
      {
        "turns": 9,
        "players": 338
      },
      {
        "turns": 10,
        "players": 567
      },
      {
        "turns": 11,
        "players": 630
      },
      {
        "turns": 12,
        "players": 559
      },
      {
        "turns": 13,
        "players": 449
      },
      {
        "turns": 14,
        "players": 361
      },
      {
        "turns": 15,
        "players": 325
      },
      {
        "turns": 16,
        "players": 258
      },
      {
        "turns": 17,
        "players": 240
      },
      {
        "turns": 18,
        "players": 178
      },
      {
        "turns": 19,
        "players": 174
      },
      {
        "turns": 20,
        "players": 133
      },
      {
        "turns": 21,
        "players": 99
      },
      {
        "turns": 22,
        "players": 70
      },
      {
        "turns": 23,
        "players": 61
      },
      {
        "turns": 24,
        "players": 43
      },
      {
        "turns": 25,
        "players": 43
      },
      {
        "turns": 26,
        "players": 36
      },
      {
        "turns": 27,
        "players": 38
      },
      {
        "turns": 28,
        "players": 27
      },
      {
        "turns": 29,
        "players": 19
      },
      {
        "turns": 30,
        "players": 12
      },
      {
        "turns": 31,
        "players": 14
      },
      {
        "turns": 32,
        "players": 7
      },
      {
        "turns": 33,
        "players": 14
      },
      {
        "turns": 34,
        "players": 9
      },
      {
        "turns": 35,
        "players": 8
      },
      {
        "turns": 36,
        "players": 5
      },
      {
        "turns": 37,
        "players": 6
      },
      {
        "turns": 38,
        "players": 4
      },
      {
        "turns": 39,
        "players": 0
      },
      {
        "turns": 40,
        "players": 6
      },
      {
        "turns": 41,
        "players": 4
      },
      {
        "turns": 42,
        "players": 2
      },
      {
        "turns": 43,
        "players": 3
      },
      {
        "turns": 44,
        "players": 4
      },
      {
        "turns": 45,
        "players": 2
      },
      {
        "turns": 46,
        "players": 4
      },
      {
        "turns": 47,
        "players": 3
      },
      {
        "turns": 48,
        "players": 0
      },
      {
        "turns": 49,
        "players": 0
      },
      {
        "turns": 50,
        "players": 0
      }
    ]
  }
}