{
  "metadata": {
    "levelId": "l-mitsumata",
    "levelName": "Mitsumata",
    "generatedAt": "2024-09-15T15:15:48.772Z",
    "expeditionId": "x-community-maps",
    "expeditionName": "Mapmaker's Archipelago"
  },
  "outcomes": {
    "lost": 498,
    "won-hard": 2312,
    "won-normal": 1746
  },
  "players": 4556,
  "feedbacks": {
    "1": 10,
    "2": 4,
    "3": 12,
    "4": 58,
    "5": 189
  },
  "turnsToVictory": {
    "normal": [
      {
        "turns": 1,
        "players": 0
      },
      {
        "turns": 2,
        "players": 0
      },
      {
        "turns": 3,
        "players": 0
      },
      {
        "turns": 4,
        "players": 0
      },
      {
        "turns": 5,
        "players": 0
      },
      {
        "turns": 6,
        "players": 0
      },
      {
        "turns": 7,
        "players": 0
      },
      {
        "turns": 8,
        "players": 0
      },
      {
        "turns": 9,
        "players": 0
      },
      {
        "turns": 10,
        "players": 0
      },
      {
        "turns": 11,
        "players": 0
      },
      {
        "turns": 12,
        "players": 0
      },
      {
        "turns": 13,
        "players": 0
      },
      {
        "turns": 14,
        "players": 0
      },
      {
        "turns": 15,
        "players": 0
      },
      {
        "turns": 16,
        "players": 0
      },
      {
        "turns": 17,
        "players": 9
      },
      {
        "turns": 18,
        "players": 42
      },
      {
        "turns": 19,
        "players": 88
      },
      {
        "turns": 20,
        "players": 126
      },
      {
        "turns": 21,
        "players": 152
      },
      {
        "turns": 22,
        "players": 174
      },
      {
        "turns": 23,
        "players": 179
      },
      {
        "turns": 24,
        "players": 157
      },
      {
        "turns": 25,
        "players": 134
      },
      {
        "turns": 26,
        "players": 111
      },
      {
        "turns": 27,
        "players": 111
      },
      {
        "turns": 28,
        "players": 71
      },
      {
        "turns": 29,
        "players": 53
      },
      {
        "turns": 30,
        "players": 68
      },
      {
        "turns": 31,
        "players": 61
      },
      {
        "turns": 32,
        "players": 30
      },
      {
        "turns": 33,
        "players": 30
      },
      {
        "turns": 34,
        "players": 28
      },
      {
        "turns": 35,
        "players": 21
      },
      {
        "turns": 36,
        "players": 14
      },
      {
        "turns": 37,
        "players": 12
      },
      {
        "turns": 38,
        "players": 9
      },
      {
        "turns": 39,
        "players": 9
      },
      {
        "turns": 40,
        "players": 9
      },
      {
        "turns": 41,
        "players": 9
      },
      {
        "turns": 42,
        "players": 4
      },
      {
        "turns": 43,
        "players": 4
      },
      {
        "turns": 44,
        "players": 0
      },
      {
        "turns": 45,
        "players": 4
      },
      {
        "turns": 46,
        "players": 2
      },
      {
        "turns": 47,
        "players": 4
      },
      {
        "turns": 48,
        "players": 4
      },
      {
        "turns": 49,
        "players": 0
      },
      {
        "turns": 50,
        "players": 0
      }
    ],
    "hard": [
      {
        "turns": 1,
        "players": 0
      },
      {
        "turns": 2,
        "players": 0
      },
      {
        "turns": 3,
        "players": 0
      },
      {
        "turns": 4,
        "players": 0
      },
      {
        "turns": 5,
        "players": 0
      },
      {
        "turns": 6,
        "players": 0
      },
      {
        "turns": 7,
        "players": 0
      },
      {
        "turns": 8,
        "players": 0
      },
      {
        "turns": 9,
        "players": 0
      },
      {
        "turns": 10,
        "players": 0
      },
      {
        "turns": 11,
        "players": 0
      },
      {
        "turns": 12,
        "players": 0
      },
      {
        "turns": 13,
        "players": 0
      },
      {
        "turns": 14,
        "players": 0
      },
      {
        "turns": 15,
        "players": 0
      },
      {
        "turns": 16,
        "players": 8
      },
      {
        "turns": 17,
        "players": 47
      },
      {
        "turns": 18,
        "players": 106
      },
      {
        "turns": 19,
        "players": 163
      },
      {
        "turns": 20,
        "players": 187
      },
      {
        "turns": 21,
        "players": 210
      },
      {
        "turns": 22,
        "players": 226
      },
      {
        "turns": 23,
        "players": 202
      },
      {
        "turns": 24,
        "players": 183
      },
      {
        "turns": 25,
        "players": 148
      },
      {
        "turns": 26,
        "players": 132
      },
      {
        "turns": 27,
        "players": 97
      },
      {
        "turns": 28,
        "players": 103
      },
      {
        "turns": 29,
        "players": 79
      },
      {
        "turns": 30,
        "players": 80
      },
      {
        "turns": 31,
        "players": 52
      },
      {
        "turns": 32,
        "players": 45
      },
      {
        "turns": 33,
        "players": 34
      },
      {
        "turns": 34,
        "players": 36
      },
      {
        "turns": 35,
        "players": 30
      },
      {
        "turns": 36,
        "players": 25
      },
      {
        "turns": 37,
        "players": 20
      },
      {
        "turns": 38,
        "players": 18
      },
      {
        "turns": 39,
        "players": 9
      },
      {
        "turns": 40,
        "players": 7
      },
      {
        "turns": 41,
        "players": 6
      },
      {
        "turns": 42,
        "players": 8
      },
      {
        "turns": 43,
        "players": 2
      },
      {
        "turns": 44,
        "players": 2
      },
      {
        "turns": 45,
        "players": 5
      },
      {
        "turns": 46,
        "players": 5
      },
      {
        "turns": 47,
        "players": 6
      },
      {
        "turns": 48,
        "players": 0
      },
      {
        "turns": 49,
        "players": 0
      },
      {
        "turns": 50,
        "players": 2
      }
    ]
  }
}