{
  "metadata": {
    "levelId": "l-moldova-1829",
    "levelName": "Moldova 1829",
    "generatedAt": "2024-07-07T18:33:56.830Z",
    "expeditionId": "x-community-maps",
    "expeditionName": "Mapmaker's Archipelago"
  },
  "outcomes": {
    "lost": 920,
    "won-hard": 1716,
    "won-normal": 881
  },
  "players": 3517,
  "feedbacks": {
    "1": 14,
    "2": 10,
    "3": 14,
    "4": 33,
    "5": 158
  },
  "turnsToVictory": {
    "normal": [
      {
        "turns": 1,
        "players": 0
      },
      {
        "turns": 2,
        "players": 0
      },
      {
        "turns": 3,
        "players": 0
      },
      {
        "turns": 4,
        "players": 0
      },
      {
        "turns": 5,
        "players": 0
      },
      {
        "turns": 6,
        "players": 0
      },
      {
        "turns": 7,
        "players": 0
      },
      {
        "turns": 8,
        "players": 0
      },
      {
        "turns": 9,
        "players": 0
      },
      {
        "turns": 10,
        "players": 0
      },
      {
        "turns": 11,
        "players": 0
      },
      {
        "turns": 12,
        "players": 0
      },
      {
        "turns": 13,
        "players": 0
      },
      {
        "turns": 14,
        "players": 6
      },
      {
        "turns": 15,
        "players": 7
      },
      {
        "turns": 16,
        "players": 20
      },
      {
        "turns": 17,
        "players": 36
      },
      {
        "turns": 18,
        "players": 51
      },
      {
        "turns": 19,
        "players": 45
      },
      {
        "turns": 20,
        "players": 61
      },
      {
        "turns": 21,
        "players": 64
      },
      {
        "turns": 22,
        "players": 63
      },
      {
        "turns": 23,
        "players": 64
      },
      {
        "turns": 24,
        "players": 55
      },
      {
        "turns": 25,
        "players": 50
      },
      {
        "turns": 26,
        "players": 50
      },
      {
        "turns": 27,
        "players": 36
      },
      {
        "turns": 28,
        "players": 28
      },
      {
        "turns": 29,
        "players": 29
      },
      {
        "turns": 30,
        "players": 31
      },
      {
        "turns": 31,
        "players": 23
      },
      {
        "turns": 32,
        "players": 20
      },
      {
        "turns": 33,
        "players": 21
      },
      {
        "turns": 34,
        "players": 21
      },
      {
        "turns": 35,
        "players": 13
      },
      {
        "turns": 36,
        "players": 11
      },
      {
        "turns": 37,
        "players": 10
      },
      {
        "turns": 38,
        "players": 9
      },
      {
        "turns": 39,
        "players": 3
      },
      {
        "turns": 40,
        "players": 5
      },
      {
        "turns": 41,
        "players": 9
      },
      {
        "turns": 42,
        "players": 6
      },
      {
        "turns": 43,
        "players": 4
      },
      {
        "turns": 44,
        "players": 5
      },
      {
        "turns": 45,
        "players": 3
      },
      {
        "turns": 46,
        "players": 7
      },
      {
        "turns": 47,
        "players": 6
      },
      {
        "turns": 48,
        "players": 2
      },
      {
        "turns": 49,
        "players": 0
      },
      {
        "turns": 50,
        "players": 0
      }
    ],
    "hard": [
      {
        "turns": 1,
        "players": 0
      },
      {
        "turns": 2,
        "players": 0
      },
      {
        "turns": 3,
        "players": 0
      },
      {
        "turns": 4,
        "players": 0
      },
      {
        "turns": 5,
        "players": 0
      },
      {
        "turns": 6,
        "players": 0
      },
      {
        "turns": 7,
        "players": 0
      },
      {
        "turns": 8,
        "players": 0
      },
      {
        "turns": 9,
        "players": 0
      },
      {
        "turns": 10,
        "players": 0
      },
      {
        "turns": 11,
        "players": 0
      },
      {
        "turns": 12,
        "players": 2
      },
      {
        "turns": 13,
        "players": 7
      },
      {
        "turns": 14,
        "players": 20
      },
      {
        "turns": 15,
        "players": 44
      },
      {
        "turns": 16,
        "players": 61
      },
      {
        "turns": 17,
        "players": 81
      },
      {
        "turns": 18,
        "players": 96
      },
      {
        "turns": 19,
        "players": 140
      },
      {
        "turns": 20,
        "players": 133
      },
      {
        "turns": 21,
        "players": 143
      },
      {
        "turns": 22,
        "players": 112
      },
      {
        "turns": 23,
        "players": 115
      },
      {
        "turns": 24,
        "players": 93
      },
      {
        "turns": 25,
        "players": 101
      },
      {
        "turns": 26,
        "players": 77
      },
      {
        "turns": 27,
        "players": 70
      },
      {
        "turns": 28,
        "players": 69
      },
      {
        "turns": 29,
        "players": 56
      },
      {
        "turns": 30,
        "players": 44
      },
      {
        "turns": 31,
        "players": 30
      },
      {
        "turns": 32,
        "players": 26
      },
      {
        "turns": 33,
        "players": 21
      },
      {
        "turns": 34,
        "players": 24
      },
      {
        "turns": 35,
        "players": 19
      },
      {
        "turns": 36,
        "players": 18
      },
      {
        "turns": 37,
        "players": 17
      },
      {
        "turns": 38,
        "players": 9
      },
      {
        "turns": 39,
        "players": 7
      },
      {
        "turns": 40,
        "players": 11
      },
      {
        "turns": 41,
        "players": 7
      },
      {
        "turns": 42,
        "players": 5
      },
      {
        "turns": 43,
        "players": 7
      },
      {
        "turns": 44,
        "players": 9
      },
      {
        "turns": 45,
        "players": 2
      },
      {
        "turns": 46,
        "players": 2
      },
      {
        "turns": 47,
        "players": 7
      },
      {
        "turns": 48,
        "players": 4
      },
      {
        "turns": 49,
        "players": 2
      },
      {
        "turns": 50,
        "players": 4
      }
    ]
  }
}