{
  "metadata": {
    "levelId": "l-occupation",
    "levelName": "Occupation",
    "generatedAt": "2025-02-28T17:32:43.135Z",
    "expeditionId": "x-experimental",
    "expeditionName": "Unstable Vortex"
  },
  "outcomes": {
    "lost": 3351,
    "won-hard": 3200,
    "won-normal": 3032
  },
  "players": 9583,
  "feedbacks": {
    "1": 40,
    "2": 24,
    "3": 36,
    "4": 80,
    "5": 293
  },
  "turnsToVictory": {
    "normal": [
      {
        "turns": 1,
        "players": 0
      },
      {
        "turns": 2,
        "players": 0
      },
      {
        "turns": 3,
        "players": 0
      },
      {
        "turns": 4,
        "players": 0
      },
      {
        "turns": 5,
        "players": 0
      },
      {
        "turns": 6,
        "players": 0
      },
      {
        "turns": 7,
        "players": 0
      },
      {
        "turns": 8,
        "players": 0
      },
      {
        "turns": 9,
        "players": 0
      },
      {
        "turns": 10,
        "players": 0
      },
      {
        "turns": 11,
        "players": 0
      },
      {
        "turns": 12,
        "players": 0
      },
      {
        "turns": 13,
        "players": 0
      },
      {
        "turns": 14,
        "players": 0
      },
      {
        "turns": 15,
        "players": 2
      },
      {
        "turns": 16,
        "players": 10
      },
      {
        "turns": 17,
        "players": 22
      },
      {
        "turns": 18,
        "players": 22
      },
      {
        "turns": 19,
        "players": 51
      },
      {
        "turns": 20,
        "players": 86
      },
      {
        "turns": 21,
        "players": 83
      },
      {
        "turns": 22,
        "players": 107
      },
      {
        "turns": 23,
        "players": 127
      },
      {
        "turns": 24,
        "players": 151
      },
      {
        "turns": 25,
        "players": 164
      },
      {
        "turns": 26,
        "players": 130
      },
      {
        "turns": 27,
        "players": 158
      },
      {
        "turns": 28,
        "players": 147
      },
      {
        "turns": 29,
        "players": 153
      },
      {
        "turns": 30,
        "players": 155
      },
      {
        "turns": 31,
        "players": 122
      },
      {
        "turns": 32,
        "players": 129
      },
      {
        "turns": 33,
        "players": 106
      },
      {
        "turns": 34,
        "players": 124
      },
      {
        "turns": 35,
        "players": 105
      },
      {
        "turns": 36,
        "players": 98
      },
      {
        "turns": 37,
        "players": 94
      },
      {
        "turns": 38,
        "players": 78
      },
      {
        "turns": 39,
        "players": 60
      },
      {
        "turns": 40,
        "players": 65
      },
      {
        "turns": 41,
        "players": 45
      },
      {
        "turns": 42,
        "players": 53
      },
      {
        "turns": 43,
        "players": 40
      },
      {
        "turns": 44,
        "players": 36
      },
      {
        "turns": 45,
        "players": 33
      },
      {
        "turns": 46,
        "players": 31
      },
      {
        "turns": 47,
        "players": 30
      },
      {
        "turns": 48,
        "players": 13
      },
      {
        "turns": 49,
        "players": 20
      },
      {
        "turns": 50,
        "players": 14
      }
    ],
    "hard": [
      {
        "turns": 1,
        "players": 0
      },
      {
        "turns": 2,
        "players": 0
      },
      {
        "turns": 3,
        "players": 0
      },
      {
        "turns": 4,
        "players": 0
      },
      {
        "turns": 5,
        "players": 0
      },
      {
        "turns": 6,
        "players": 0
      },
      {
        "turns": 7,
        "players": 0
      },
      {
        "turns": 8,
        "players": 0
      },
      {
        "turns": 9,
        "players": 0
      },
      {
        "turns": 10,
        "players": 0
      },
      {
        "turns": 11,
        "players": 0
      },
      {
        "turns": 12,
        "players": 0
      },
      {
        "turns": 13,
        "players": 0
      },
      {
        "turns": 14,
        "players": 4
      },
      {
        "turns": 15,
        "players": 4
      },
      {
        "turns": 16,
        "players": 4
      },
      {
        "turns": 17,
        "players": 9
      },
      {
        "turns": 18,
        "players": 18
      },
      {
        "turns": 19,
        "players": 38
      },
      {
        "turns": 20,
        "players": 46
      },
      {
        "turns": 21,
        "players": 74
      },
      {
        "turns": 22,
        "players": 82
      },
      {
        "turns": 23,
        "players": 112
      },
      {
        "turns": 24,
        "players": 98
      },
      {
        "turns": 25,
        "players": 117
      },
      {
        "turns": 26,
        "players": 144
      },
      {
        "turns": 27,
        "players": 127
      },
      {
        "turns": 28,
        "players": 117
      },
      {
        "turns": 29,
        "players": 147
      },
      {
        "turns": 30,
        "players": 135
      },
      {
        "turns": 31,
        "players": 146
      },
      {
        "turns": 32,
        "players": 121
      },
      {
        "turns": 33,
        "players": 142
      },
      {
        "turns": 34,
        "players": 99
      },
      {
        "turns": 35,
        "players": 103
      },
      {
        "turns": 36,
        "players": 113
      },
      {
        "turns": 37,
        "players": 109
      },
      {
        "turns": 38,
        "players": 99
      },
      {
        "turns": 39,
        "players": 88
      },
      {
        "turns": 40,
        "players": 78
      },
      {
        "turns": 41,
        "players": 69
      },
      {
        "turns": 42,
        "players": 64
      },
      {
        "turns": 43,
        "players": 73
      },
      {
        "turns": 44,
        "players": 57
      },
      {
        "turns": 45,
        "players": 51
      },
      {
        "turns": 46,
        "players": 48
      },
      {
        "turns": 47,
        "players": 45
      },
      {
        "turns": 48,
        "players": 30
      },
      {
        "turns": 49,
        "players": 32
      },
      {
        "turns": 50,
        "players": 36
      }
    ]
  }
}