{
  "metadata": {
    "levelId": "l-yang",
    "levelName": "Yang",
    "generatedAt": "2024-08-18T13:15:24.207Z",
    "expeditionId": "x-old-world",
    "expeditionName": "Old World"
  },
  "outcomes": {
    "lost": 899,
    "won-hard": 1854,
    "won-normal": 3935
  },
  "players": 6688,
  "feedbacks": {
    "1": 24,
    "2": 18,
    "3": 32,
    "4": 104,
    "5": 380
  },
  "turnsToVictory": {
    "normal": [
      {
        "turns": 1,
        "players": 0
      },
      {
        "turns": 2,
        "players": 0
      },
      {
        "turns": 3,
        "players": 0
      },
      {
        "turns": 4,
        "players": 0
      },
      {
        "turns": 5,
        "players": 0
      },
      {
        "turns": 6,
        "players": 0
      },
      {
        "turns": 7,
        "players": 0
      },
      {
        "turns": 8,
        "players": 6
      },
      {
        "turns": 9,
        "players": 16
      },
      {
        "turns": 10,
        "players": 55
      },
      {
        "turns": 11,
        "players": 89
      },
      {
        "turns": 12,
        "players": 164
      },
      {
        "turns": 13,
        "players": 229
      },
      {
        "turns": 14,
        "players": 243
      },
      {
        "turns": 15,
        "players": 274
      },
      {
        "turns": 16,
        "players": 287
      },
      {
        "turns": 17,
        "players": 283
      },
      {
        "turns": 18,
        "players": 256
      },
      {
        "turns": 19,
        "players": 303
      },
      {
        "turns": 20,
        "players": 213
      },
      {
        "turns": 21,
        "players": 216
      },
      {
        "turns": 22,
        "players": 159
      },
      {
        "turns": 23,
        "players": 157
      },
      {
        "turns": 24,
        "players": 135
      },
      {
        "turns": 25,
        "players": 122
      },
      {
        "turns": 26,
        "players": 79
      },
      {
        "turns": 27,
        "players": 97
      },
      {
        "turns": 28,
        "players": 76
      },
      {
        "turns": 29,
        "players": 77
      },
      {
        "turns": 30,
        "players": 65
      },
      {
        "turns": 31,
        "players": 49
      },
      {
        "turns": 32,
        "players": 40
      },
      {
        "turns": 33,
        "players": 35
      },
      {
        "turns": 34,
        "players": 31
      },
      {
        "turns": 35,
        "players": 22
      },
      {
        "turns": 36,
        "players": 20
      },
      {
        "turns": 37,
        "players": 23
      },
      {
        "turns": 38,
        "players": 14
      },
      {
        "turns": 39,
        "players": 7
      },
      {
        "turns": 40,
        "players": 13
      },
      {
        "turns": 41,
        "players": 6
      },
      {
        "turns": 42,
        "players": 10
      },
      {
        "turns": 43,
        "players": 4
      },
      {
        "turns": 44,
        "players": 7
      },
      {
        "turns": 45,
        "players": 9
      },
      {
        "turns": 46,
        "players": 4
      },
      {
        "turns": 47,
        "players": 4
      },
      {
        "turns": 48,
        "players": 5
      },
      {
        "turns": 49,
        "players": 0
      },
      {
        "turns": 50,
        "players": 2
      }
    ],
    "hard": [
      {
        "turns": 1,
        "players": 0
      },
      {
        "turns": 2,
        "players": 0
      },
      {
        "turns": 3,
        "players": 0
      },
      {
        "turns": 4,
        "players": 0
      },
      {
        "turns": 5,
        "players": 0
      },
      {
        "turns": 6,
        "players": 0
      },
      {
        "turns": 7,
        "players": 2
      },
      {
        "turns": 8,
        "players": 13
      },
      {
        "turns": 9,
        "players": 27
      },
      {
        "turns": 10,
        "players": 74
      },
      {
        "turns": 11,
        "players": 76
      },
      {
        "turns": 12,
        "players": 105
      },
      {
        "turns": 13,
        "players": 107
      },
      {
        "turns": 14,
        "players": 105
      },
      {
        "turns": 15,
        "players": 99
      },
      {
        "turns": 16,
        "players": 117
      },
      {
        "turns": 17,
        "players": 113
      },
      {
        "turns": 18,
        "players": 137
      },
      {
        "turns": 19,
        "players": 102
      },
      {
        "turns": 20,
        "players": 99
      },
      {
        "turns": 21,
        "players": 85
      },
      {
        "turns": 22,
        "players": 77
      },
      {
        "turns": 23,
        "players": 58
      },
      {
        "turns": 24,
        "players": 57
      },
      {
        "turns": 25,
        "players": 62
      },
      {
        "turns": 26,
        "players": 53
      },
      {
        "turns": 27,
        "players": 37
      },
      {
        "turns": 28,
        "players": 25
      },
      {
        "turns": 29,
        "players": 32
      },
      {
        "turns": 30,
        "players": 34
      },
      {
        "turns": 31,
        "players": 26
      },
      {
        "turns": 32,
        "players": 29
      },
      {
        "turns": 33,
        "players": 14
      },
      {
        "turns": 34,
        "players": 12
      },
      {
        "turns": 35,
        "players": 14
      },
      {
        "turns": 36,
        "players": 6
      },
      {
        "turns": 37,
        "players": 8
      },
      {
        "turns": 38,
        "players": 6
      },
      {
        "turns": 39,
        "players": 6
      },
      {
        "turns": 40,
        "players": 2
      },
      {
        "turns": 41,
        "players": 4
      },
      {
        "turns": 42,
        "players": 3
      },
      {
        "turns": 43,
        "players": 2
      },
      {
        "turns": 44,
        "players": 3
      },
      {
        "turns": 45,
        "players": 2
      },
      {
        "turns": 46,
        "players": 2
      },
      {
        "turns": 47,
        "players": 3
      },
      {
        "turns": 48,
        "players": 0
      },
      {
        "turns": 49,
        "players": 0
      },
      {
        "turns": 50,
        "players": 0
      }
    ]
  }
}